etltk/__init__.py
etltk/common/__init__.py
etltk/common/doc.py
etltk/lang/__init__.py
etltk/lang/am/__init__.py
etltk/lang/am/normalizer.py
etltk/lang/am/preprocessing.py
etltk/lang/am/punctuation.py
etltk/lang/am/stop_words.py
etltk/lang/am/utils.py
etltk/lang/am/data/__init__.py
etltk/lang/am/data/char_replacers_dict.json
etltk/lang/am/data/labialized_dict.json
etltk/lang/am/data/punct_replacers_dict.json
etltk/lang/am/data/shortened_expansions_dict.json
etltk/tokenize/__init__.py
etltk/tokenize/am.py
etltk/tokenize/line.py
etltk/tokenize/or.py
etltk/tokenize/regexp.py
etltk/tokenize/space.py
etltk-0.0.22.dist-info/LICENSE.txt
etltk-0.0.22.dist-info/METADATA
etltk-0.0.22.dist-info/WHEEL
etltk-0.0.22.dist-info/top_level.txt
etltk-0.0.22.dist-info/RECORD
